[[{"location":"C:\\Users\\Dev\\Desktop\\AndroidWebinar\\Metaio SDK 6.0.1\\_Android\\metaioSDK\\bin\\metaiosdk.jar","type":"JAR","hints":{}},"ABSENT"],[{"location":"C:\\Users\\Dev\\AppData\\Local\\Android\\sdk\\platforms\\android-21\\android.jar","type":"JAR","hints":{}},"ABSENT"],[{"location":"C:\\Users\\Dev\\Desktop\\AndroidWebinar\\appcompat_v7\\libs\\android-support-v7-appcompat.jar","type":"JAR","hints":{}},"ABSENT"],[{"location":"C:\\Users\\Dev\\Desktop\\AndroidWebinar\\App123","type":"PROJECT","hints":{"PROJECT_NAME":"App123"}},"ABSENT"],[{"location":"C:\\Users\\Dev\\Desktop\\AndroidWebinar\\Metaio SDK 6.0.1\\_Android\\metaioSDK\\libs\\metaiosdk.jar","type":"JAR","hints":{}},"ABSENT"]]